{
    "boundaryYearRepresented": 2019,
    "boundaryISO": "PNG",
    "boundaryType": "ADM2",
    "boundaryCanonical": "District",
    "boundaryLicense": "Creative Commons Attribution International",
    "nameField": "adm2_name",
    "licenseDetail": null,
    "licenseSource": "https://data.humdata.org/dataset/wfp-geonode-papua-new-guinea-admin-boundaries-level-2-districts",
    "boundarySourceURL": "https://data.humdata.org/dataset/wfp-geonode-papua-new-guinea-admin-boundaries-level-2-districts",
    "sourceDataUpdateDate": "17 April 2020",
    "boundarySource-1": "World Food Programme",
    "boundarySource-2": "Geoenabler"
}