{
 "input": [
  {
   "path": "URY.zip/osm_URY_2.shp",
   "level": 0,
   "type": null,
   "name_field": "name"
  },
  {
   "path": "URY.zip/osm_URY_4.shp",
   "level": 1,
   "type": null,
   "name_field": "name"
  }
 ],
 "year": null,
 "iso": "URY",
 "source": [
  "OSM-Boundaries",
  "OpenStreetMap"
 ],
 "source_updated": "2021-07-12",
 "source_url": "https://osm-boundaries.com/",
 "license": "OpenStreetMap License",
 "license_detail": "Creative Commons Attribution-ShareAlike 2.0",
 "license_url": "www.openstreetmap.org/copyright"
}