{
    "input": "SEN_2008_07_10_SALB.zip/BNDA_SEN_2008-07-10_present.shp",
    "iso": "SEN",
    "year": 2021,
    "level": 2,
    "type_field": null,
    "name_field": "ADM2NM",
    "source": [
        "UN SALB"
    ],
    "source_updated": "2021-03-16",
    "source_url": "https://www.unsalb.org/data/sen",
    "download_url": "https://www.unsalb.org/data/sen",
    "license": "UN SALB Data License",
    "license_detail": null,
    "license_url": "https://www.unsalb.org/sites/default/files/wysiwyg_uploads/docs_uploads/TermsOfUseSALB2021.pdf"
}